[{"name":"Juzi_CN","rank":"Guild Master","joined":"2022年08月09日11时51分44秒"},{"name":"7ulyer","rank":"副会长","joined":"2024年04月04日19时54分07秒"},{"name":"_Starquakes_","rank":"公会骨干","joined":"2024年02月13日19时31分26秒"},{"name":"SzCaa","rank":"公会骨干","joined":"2023年03月11日17时41分15秒"},{"name":"whypoor","rank":"公会骨干","joined":"2024年02月22日11时00分55秒"},{"name":"DianZanGuanZhu","rank":"公会骨干","joined":"2024年02月20日22时24分02秒"},{"name":"lateritious","rank":"公会骨干","joined":"2024年02月20日18时51分14秒"},{"name":"GordonSwearing","rank":"公会骨干","joined":"2024年02月20日17时24分28秒"},{"name":"Jackfiniy","rank":"公会骨干","joined":"2023年08月10日14时10分46秒"},{"name":"SadHiz","rank":"公会骨干","joined":"2024年02月10日11时29分06秒"},{"name":"LEGENDARYXC","rank":"公会骨干","joined":"2023年03月05日10时02分57秒"},{"name":"WhyHit","rank":"公会骨干","joined":"2023年12月29日23时55分22秒"},{"name":"TheBestALuo","rank":"公会骨干","joined":"2023年12月26日00时12分44秒"},{"name":"skybooko","rank":"公会骨干","joined":"2022年09月03日21时35分31秒"},{"name":"_LXH","rank":"公会骨干","joined":"2023年10月27日19时51分04秒"},{"name":"_v50","rank":"公会骨干","joined":"2023年12月23日19时13分01秒"},{"name":"bwnb","rank":"公会骨干","joined":"2023年12月21日21时35分04秒"},{"name":"lroe","rank":"公会骨干","joined":"2023年03月10日21时30分01秒"},{"name":"evx4","rank":"公会骨干","joined":"2024年02月24日11时16分59秒"},{"name":"SaoHuangDaDui","rank":"公会骨干","joined":"2023年12月07日22时03分18秒"},{"name":"0Ava","rank":"公会骨干","joined":"2024年03月09日21时38分14秒"},{"name":"BHCN","rank":"公会骨干","joined":"2024年04月06日20时21分09秒"},{"name":"Zossil","rank":"公会骨干","joined":"2023年02月18日20时51分35秒"},{"name":"im_Aniya","rank":"公会骨干","joined":"2023年01月15日12时16分02秒"},{"name":"ImOldBig","rank":"公会骨干","joined":"2022年10月22日12时17分17秒"},{"name":"7Yue","rank":"公会骨干","joined":"2024年03月16日22时25分49秒"},{"name":"Aa_Koishi_2015","rank":"公会骨干","joined":"2024年03月09日17时45分56秒"},{"name":"ZiEric","rank":"公会骨干","joined":"2023年01月11日20时34分17秒"},{"name":"An5ue","rank":"公会骨干","joined":"2024年03月15日23时06分02秒"},{"name":"2UTOMAYO","rank":"公会骨干","joined":"2024年03月12日22时50分14秒"},{"name":"SpaceSheepL","rank":"公会高管","joined":"2024年03月17日10时47分36秒"},{"name":"Qiuda_","rank":"公会高管","joined":"2024年02月04日16时05分28秒"},{"name":"Yuo1","rank":"公会高管","joined":"2024年02月04日16时06分58秒"},{"name":"YTSky","rank":"公会高管","joined":"2024年03月03日00时02分20秒"},{"name":"_xLuo_","rank":"公会高管","joined":"2024年03月09日19时55分45秒"},{"name":"nyachuletaxiaoE","rank":"公会高管","joined":"2023年06月23日10时38分28秒"},{"name":"A9RiL","rank":"公会高管","joined":"2023年03月19日13时43分35秒"},{"name":"Charlotte_GG","rank":"公会高管","joined":"2024年02月12日20时09分55秒"},{"name":"FilledCh0c0late","rank":"公会高管","joined":"2023年01月10日22时06分12秒"},{"name":"Its_love","rank":"公会高管","joined":"2024年02月20日17时27分51秒"},{"name":"MEICHIFAN","rank":"公会协管","joined":"2024年02月22日21时16分38秒"},{"name":"Waterity","rank":"公会协管","joined":"2024年02月03日20时12分49秒"},{"name":"Hrar","rank":"公会协管","joined":"2024年01月24日19时04分47秒"},{"name":"Dewi3r","rank":"公会协管","joined":"2024年01月13日17时40分18秒"},{"name":"74R","rank":"公会协管","joined":"2024年02月12日21时04分46秒"},{"name":"NayiKz","rank":"公会协管","joined":"2023年12月06日22时28分03秒"},{"name":"YueFa","rank":"公会协管","joined":"2024年03月24日00时03分27秒"},{"name":"F740","rank":"公会协管","joined":"2024年04月04日09时49分10秒"},{"name":"Tkula","rank":"公会协管","joined":"2024年03月08日22时28分02秒"},{"name":"I0ng","rank":"公会协管","joined":"2024年03月01日20时46分51秒"},{"name":"NotT47","rank":"公会协管","joined":"2023年12月17日13时07分04秒"},{"name":"heoq","rank":"公会协管","joined":"2023年12月10日23时20分39秒"},{"name":"LostPigYoo","rank":"公会协管","joined":"2024年01月13日10时47分32秒"},{"name":"Kaizu_kun","rank":"公会协管","joined":"2023年12月23日20时46分23秒"},{"name":"Z408","rank":"公会协管","joined":"2022年12月31日21时24分29秒"},{"name":"Cat_cheng","rank":"公会协管","joined":"2023年11月05日21时53分33秒"},{"name":"Inory","rank":"公会协管","joined":"2023年09月10日22时00分07秒"},{"name":"Skillo89","rank":"公会协管","joined":"2023年03月05日09时15分27秒"},{"name":"CHY_QAQ","rank":"公会协管","joined":"2023年08月10日15时38分07秒"},{"name":"HypixelFather","rank":"公会协管","joined":"2023年10月14日10时41分14秒"},{"name":"CheatingF0rFun","rank":"公会协管","joined":"2023年03月05日11时06分48秒"},{"name":"hai_pao","rank":"公会协管","joined":"2023年07月04日22时28分23秒"},{"name":"mushroom_Jun","rank":"公会成员","joined":"2023年03月05日09时21分33秒"},{"name":"ShengKings_","rank":"公会成员","joined":"2024年03月03日16时39分25秒"},{"name":"Laganet","rank":"公会成员","joined":"2024年03月14日19时05分01秒"},{"name":"Bydwars","rank":"公会成员","joined":"2024年02月24日14时13分36秒"},{"name":"Yukion_","rank":"公会成员","joined":"2024年03月08日22时30分30秒"},{"name":"snowcovershabi","rank":"公会成员","joined":"2024年03月09日17时28分33秒"},{"name":"NotC_Eric_zi","rank":"公会成员","joined":"2023年01月12日19时58分25秒"},{"name":"Amrsky","rank":"公会成员","joined":"2023年01月07日11时48分09秒"},{"name":"oceanbooko","rank":"公会成员","joined":"2023年01月06日16时21分43秒"},{"name":"wwly","rank":"公会成员","joined":"2023年12月03日22时41分39秒"},{"name":"StrangeMedusa29","rank":"公会成员","joined":"2022年12月28日13时01分00秒"},{"name":"Canallzy","rank":"公会成员","joined":"2024年03月14日21时19分58秒"},{"name":"1mol_YuYuan","rank":"公会成员","joined":"2024年03月29日21时26分25秒"},{"name":"chushi_cook","rank":"公会成员","joined":"2024年04月21日00时23分26秒"},{"name":"HuanYaoo","rank":"公会成员","joined":"2024年04月20日17时08分14秒"},{"name":"a_golden_block","rank":"公会成员","joined":"2022年09月11日14时43分13秒"},{"name":"3430","rank":"公会成员","joined":"2022年09月17日20时57分20秒"},{"name":"Maimang_wheat","rank":"公会成员","joined":"2022年11月30日10时45分46秒"},{"name":"QeeYuEr","rank":"公会成员","joined":"2024年03月30日13时01分28秒"},{"name":"Marmalade_TnT","rank":"公会成员","joined":"2024年03月27日12时32分52秒"},{"name":"badbears","rank":"公会成员","joined":"2023年07月14日19时55分10秒"},{"name":"warm_light_","rank":"公会成员","joined":"2022年12月03日21时33分21秒"},{"name":"WithU_","rank":"公会成员","joined":"2024年03月23日21时46分43秒"},{"name":"9Yue","rank":"公会成员","joined":"2024年03月17日19时32分14秒"},{"name":"Axyiii","rank":"公会成员","joined":"2022年12月10日20时58分39秒"},{"name":"_________IIII","rank":"公会成员","joined":"2022年12月11日20时12分09秒"},{"name":"qp3","rank":"公会成员","joined":"2024年03月16日18时37分47秒"},{"name":"Badcat_cute","rank":"公会成员","joined":"2023年07月05日09时57分17秒"},{"name":"ICE_fu","rank":"公会成员","joined":"2023年07月19日12时15分18秒"},{"name":"Relacty","rank":"公会成员","joined":"2024年02月21日16时35分28秒"},{"name":"13M_","rank":"公会成员","joined":"2024年01月24日10时41分44秒"},{"name":"NeedyAngel_","rank":"公会成员","joined":"2023年12月01日20时34分07秒"},{"name":"Mutedfor7Days","rank":"公会成员","joined":"2023年12月12日21时57分20秒"},{"name":"Gaffu_Cat","rank":"公会成员","joined":"2023年11月10日17时09分00秒"},{"name":"WanderVague","rank":"公会成员","joined":"2023年12月21日21时11分18秒"},{"name":"kskongbai","rank":"公会成员","joined":"2023年11月05日15时26分15秒"},{"name":"CosI_IX","rank":"公会成员","joined":"2023年10月15日01时09分44秒"},{"name":"L0W","rank":"公会成员","joined":"2023年10月04日19时51分58秒"},{"name":"typogalaxies1122","rank":"公会成员","joined":"2023年12月30日18时30分12秒"},{"name":"Choccolate_","rank":"公会成员","joined":"2023年12月31日08时10分37秒"},{"name":"lroj","rank":"公会成员","joined":"2023年12月31日15时16分25秒"},{"name":"iBolti","rank":"公会成员","joined":"2024年01月01日17时28分20秒"},{"name":"7237","rank":"公会成员","joined":"2024年01月06日22时05分17秒"},{"name":"ID4X","rank":"公会成员","joined":"2023年10月01日11时23分01秒"},{"name":"Whyoidless","rank":"公会成员","joined":"2023年09月30日19时03分23秒"},{"name":"OhiC","rank":"公会成员","joined":"2023年09月24日18时13分54秒"},{"name":"unrevive","rank":"公会成员","joined":"2024年02月20日23时00分42秒"},{"name":"JuziClub","rank":"公会成员","joined":"2024年01月27日19时35分19秒"},{"name":"Craipo","rank":"公会成员","joined":"2024年01月28日11时47分20秒"},{"name":"hiroro2647","rank":"公会成员","joined":"2023年09月22日17时25分13秒"},{"name":"YouAlu","rank":"公会成员","joined":"2023年08月28日12时48分53秒"},{"name":"whv1","rank":"公会成员","joined":"2024年02月07日14时49分52秒"},{"name":"BasicLeah","rank":"公会成员","joined":"2023年08月19日10时00分19秒"},{"name":"CN_TPTPya","rank":"公会成员","joined":"2023年08月15日11时28分58秒"},{"name":"2XINg","rank":"公会成员","joined":"2023年08月14日21时24分38秒"},{"name":"Cyemology","rank":"公会成员","joined":"2024年02月20日15时31分19秒"},{"name":"iamgms","rank":"公会成员","joined":"2023年08月10日12时30分10秒"},{"name":"Noth1ngButL0ve","rank":"公会成员","joined":"2023年08月09日14时32分15秒"},{"name":"Ransen11k_Sky","rank":"公会成员","joined":"2023年08月02日13时57分28秒"},{"name":"ImBigGod","rank":"公会成员","joined":"2024年02月20日19时05分43秒"},{"name":"WM_across_fire","rank":"公会成员","joined":"2023年12月02日19时53分28秒"},{"name":"Juzi_Club","rank":"公会成员","joined":"2024年04月21日08时50分09秒"}]